prompteer/__init__.py
prompteer/__main__.py
prompteer/cli.py
prompteer/core.py
prompteer/exceptions.py
prompteer/metadata.py
prompteer/path_utils.py
prompteer/proxy.py
prompteer/py.typed
prompteer/template.py
prompteer/type_generator.py
prompteer-0.2.1.dist-info/licenses/LICENSE
prompteer-0.2.1.dist-info/METADATA
prompteer-0.2.1.dist-info/WHEEL
prompteer-0.2.1.dist-info/entry_points.txt
prompteer-0.2.1.dist-info/top_level.txt
prompteer-0.2.1.dist-info/RECORD
