Metadata-Version: 2.4
Name: prompteer
Version: 0.2.1
Summary: A lightweight file-based prompt manager for LLM workflows. Simple, scalable, and version-control friendly.
Author-email: Mintae Kim <ibare77@gmail.com>
License-Expression: MIT
Project-URL: Homepage, https://github.com/ibare/prompteer
Project-URL: Documentation, https://github.com/ibare/prompteer#readme
Project-URL: Repository, https://github.com/ibare/prompteer
Project-URL: Bug Tracker, https://github.com/ibare/prompteer/issues
Keywords: prompt,llm,ai,prompt-engineering,prompt-management
Classifier: Development Status :: 3 - Alpha
Classifier: Intended Audience :: Developers
Classifier: Programming Language :: Python :: 3
Classifier: Programming Language :: Python :: 3.7
Classifier: Programming Language :: Python :: 3.8
Classifier: Programming Language :: Python :: 3.9
Classifier: Programming Language :: Python :: 3.10
Classifier: Programming Language :: Python :: 3.11
Classifier: Programming Language :: Python :: 3.12
Classifier: Topic :: Software Development :: Libraries :: Python Modules
Classifier: Topic :: Text Processing
Requires-Python: >=3.7
License-File: LICENSE
Requires-Dist: PyYAML>=5.1
Provides-Extra: dev
Requires-Dist: pytest>=6.0; extra == "dev"
Requires-Dist: pytest-cov>=2.0; extra == "dev"
Requires-Dist: black>=22.0; extra == "dev"
Requires-Dist: flake8>=4.0; extra == "dev"
Requires-Dist: mypy>=0.900; extra == "dev"
Requires-Dist: isort>=5.0; extra == "dev"
Provides-Extra: watch
Requires-Dist: watchdog>=2.0; extra == "watch"
Dynamic: license-file
